Metadata-Version: 2.1
Name: post-from-os
Version: 1.0
Summary: Opensea Sales Bots
Home-page: https://github.com/epicmanmoo/post-from-os
Author: epicmanmoo
Author-email: mooaz09@gmail.com
License: MIT
Keywords: Bots
Platform: UNKNOWN
Requires-Python: >=3.6
